rc35h/__init__.py
rc35h/__main__.py
rc35h-0.1.0.dist-info/entry_points.txt
rc35h-0.1.0.dist-info/WHEEL
rc35h-0.1.0.dist-info/METADATA
rc35h-0.1.0.dist-info/RECORD
